MANIFEST.in
README.md
setup.py
collective/__init__.py
collective.perseo.egg-info/PKG-INFO
collective.perseo.egg-info/SOURCES.txt
collective.perseo.egg-info/dependency_links.txt
collective.perseo.egg-info/entry_points.txt
collective.perseo.egg-info/namespace_packages.txt
collective.perseo.egg-info/not-zip-safe
collective.perseo.egg-info/requires.txt
collective.perseo.egg-info/top_level.txt
collective/perseo/__init__.py
collective/perseo/configure.zcml
collective/perseo/i18n.sh
collective/perseo/listMetaTags.py
collective/perseo/patches.zcml
collective/perseo/skins.zcml
collective/perseo/tests.py
collective/perseo/upgrades.py
collective/perseo/util.py
collective/perseo/browser/__init__.py
collective/perseo/browser/configure.zcml
collective/perseo/browser/event.py
collective/perseo/browser/indexers.py
collective/perseo/browser/interfaces.py
collective/perseo/browser/seo_config.py
collective/perseo/browser/sitemap.py
collective/perseo/browser/sitemap.xml
collective/perseo/browser/types.py
collective/perseo/browser/viewlets.py
collective/perseo/browser/views.py
collective/perseo/browser/resources/seo.png
collective/perseo/browser/templates/perseo_tab_context.pt
collective/perseo/browser/templates/seo-control-panel.pt
collective/perseo/locales/collective.perseo.pot
collective/perseo/locales/it/LC_MESSAGES/collective.perseo.po
collective/perseo/profiles/default/actions.xml
collective/perseo/profiles/default/browserlayer.xml
collective/perseo/profiles/default/catalog.xml
collective/perseo/profiles/default/controlpanel.xml
collective/perseo/profiles/default/metadata.xml
collective/perseo/profiles/default/rolemap.xml
collective/perseo/profiles/default/skins.xml
collective/perseo/profiles/default/viewlets.xml
collective/perseo/skins/collective.perseo.templates/rss_template.pt
collective/perseo/skins/collective.perseo.templates/rss_template.pt.metadata
docs/HISTORY.txt
docs/INSTALL.txt
docs/LICENSE.GPL
docs/LICENSE.txt