Metadata-Version: 1.1
Name: collective.perseo
Version: 0.6.5
Summary: Search Engine Optimization Package
Home-page: http://plone.org/products/collective.perseo
Author: RedTurtle Technology
Author-email: sviluppoplone@redturtle.net
License: GPL
Platform: UNKNOWN
Classifier: Framework :: Plone
Classifier: Framework :: Plone :: 4.1
Classifier: Programming Language :: Python
